wsgi_adapter/__init__.py
wsgi_adapter/handler.py
wsgi_adapter/request.py
wsgi_adapter/response.py
azure_functions_wsgi_adapter-0.2.dist-info/LICENSE
azure_functions_wsgi_adapter-0.2.dist-info/METADATA
azure_functions_wsgi_adapter-0.2.dist-info/WHEEL
azure_functions_wsgi_adapter-0.2.dist-info/top_level.txt
azure_functions_wsgi_adapter-0.2.dist-info/RECORD
