Metadata-Version: 2.1
Name: azure-functions-wsgi-adapter
Version: 0.2
Summary: Adapter to run your WSGI application in Azure Functions. 🎉
Home-page: https://github.com/carltongibson/azure-functions-wsgi-adapter
Author: Carlton Gibson
Author-email: carlton.gibson@noumenal.es
License: MIT
Platform: UNKNOWN
